pygifconvert_hoev/__init__.py
pygifconvert_hoev/converter.py
pygifconvert_hoev-3.13.2.dist-info/licenses/LICENSE
pygifconvert_hoev-3.13.2.dist-info/METADATA
pygifconvert_hoev-3.13.2.dist-info/WHEEL
pygifconvert_hoev-3.13.2.dist-info/top_level.txt
pygifconvert_hoev-3.13.2.dist-info/RECORD
